<?xml version="1.0" encoding="utf-8" ?>
<Patch>
	<Operation Class="PatchOperationAdd">
		<xpath>/Defs/FactionDef[@Name="OutlanderFactionBase"]/pawnGroupMakers/li[1]/options</xpath>  <!-- Outlander "normal" group -->
		<value>
   <!-- Pawnkinds from your race, keep points down low to avoid making your pawns a majority -->
      <!-- The more rare, the lower your points should be -->
					<Ghoul_Villager>1.5</Ghoul_Villager>
					<Ghoul_Town_Guard>3</Ghoul_Town_Guard>
					<Ghoul_Grenadier_Destructive>0.25</Ghoul_Grenadier_Destructive>
					<Ghoul_Mercenary_Slasher>2.5</Ghoul_Mercenary_Slasher>
					<Ghoul_Mercenary_Gunner>3</Ghoul_Mercenary_Gunner>
					<Ghoul_Mercenary_Elite>3</Ghoul_Mercenary_Elite>
          <Ghoul_Town_Councilman>3</Ghoul_Town_Councilman>
		</value>
	</Operation> 
	
	<Operation Class="PatchOperationAdd">
		<xpath>/Defs/FactionDef[@Name="OutlanderFactionBase"]/pawnGroupMakers/li[2]/options</xpath>  <!-- Outlander "normal" group -->
		<value>
   <!-- Pawnkinds from your race, keep points down low to avoid making your pawns a majority -->
      <!-- The more rare, the lower your points should be -->
					<Ghoul_Villager>5</Ghoul_Villager>
					<Ghoul_Town_Guard>3</Ghoul_Town_Guard>
          <Ghoul_Town_Councilman>3</Ghoul_Town_Councilman>
		</value>
	</Operation> 
	
	
	
	<Operation Class="PatchOperationAdd">
		<xpath>/Defs/FactionDef[@Name="OutlanderFactionBase"]/pawnGroupMakers/li[3]/guards</xpath>  <!-- Outlander Caravan guard group -->
		<value>
			<Ghoul_Town_Guard>3</Ghoul_Town_Guard>
			<Ghoul_Town_Councilman>3</Ghoul_Town_Councilman>
			<Ghoul_Mercenary_Slasher>1</Ghoul_Mercenary_Slasher>
		</value>
	</Operation> 
	
<Operation Class="PatchOperationAdd">
		<xpath>/Defs/FactionDef[@Name="OutlanderFactionBase"]/pawnGroupMakers/li[3]/traders</xpath>  <!-- Outlander Caravan guard group -->
		<value>
          <Ghoul_Town_Trader>0.33</Ghoul_Town_Trader>

		</value>
	</Operation> 
	
	<Operation Class="PatchOperationAdd">
		<xpath>/Defs/FactionDef[@Name="OutlanderFactionBase"]/pawnGroupMakers/li[4]/options</xpath>  <!-- Outlander base group -->
		<value>
			<Ghoul_Villager>1</Ghoul_Villager>
			<Ghoul_Town_Guard>3</Ghoul_Town_Guard>
			<Ghoul_Grenadier_Destructive>0.25</Ghoul_Grenadier_Destructive>
			<Ghoul_Mercenary_Slasher>2.5</Ghoul_Mercenary_Slasher>
			<Ghoul_Mercenary_Gunner>3</Ghoul_Mercenary_Gunner>
			<Ghoul_Mercenary_Elite>3</Ghoul_Mercenary_Elite>
			<Ghoul_Town_Councilman>10</Ghoul_Town_Councilman>
		</value>
	</Operation> 
</Patch>